hujiscrape/__init__.py
hujiscrape/fetch_tasks.py
hujiscrape/fetchers.py
hujiscrape/html_to_object.py
hujiscrape/huji_objects.py
hujiscrape/magics.py
hujiscrape/scrapers.py
hujiscrape-1.1.1.dist-info/METADATA
hujiscrape-1.1.1.dist-info/WHEEL
hujiscrape-1.1.1.dist-info/licenses/LICENSE
hujiscrape-1.1.1.dist-info/RECORD
