Metadata-Version: 2.4
Name: hujiscrape
Version: 1.1.1
Summary: A scraping tool for HUJI sites.
Project-URL: Homepage, https://github.com/yotamgod/hujiscrape
Project-URL: Source, https://github.com/yotamgod/hujiscrape
Author-email: Yotam Rosenmann <yotam.pub@gmail.com>
License: MIT License
License-File: LICENSE
Classifier: License :: OSI Approved :: MIT License
Classifier: Operating System :: OS Independent
Classifier: Programming Language :: Python :: 3
Requires-Python: <4.0,>=3.10
Requires-Dist: aiohttp>=3.12.15
Requires-Dist: beautifulsoup4<5,>=4.13.4
Requires-Dist: tqdm<5,>=4.67.1
